arson/__init__.py
arson-0.0.7.dist-info/LICENSE.txt
arson-0.0.7.dist-info/METADATA
arson-0.0.7.dist-info/WHEEL
arson-0.0.7.dist-info/top_level.txt
arson-0.0.7.dist-info/RECORD
