Metadata-Version: 2.1
Name: arson
Version: 0.0.7
Summary: A restructured object notation
Author-email: tef <tef@printf.net>
Project-URL: Homepage, https://github.com/tef/arson
Project-URL: Bug Tracker, https://github.com/tef/arson/issues
Classifier: Programming Language :: Python :: 3
Classifier: License :: OSI Approved :: MIT License
Classifier: Operating System :: OS Independent
Requires-Python: >=3.6
License-File: LICENSE.txt
